uiblack/__init__.py
uiblack/terminal.py
uiblack-1.2.2.dist-info/LICENSE
uiblack-1.2.2.dist-info/METADATA
uiblack-1.2.2.dist-info/WHEEL
uiblack-1.2.2.dist-info/top_level.txt
uiblack-1.2.2.dist-info/RECORD
