Metadata-Version: 2.1
Name: uiblack
Version: 1.2.2
Summary: Streamlined cross-platform Textual UI
Home-page: https://github.com/BlackburnHax/uiblack
Author: Brandon Blackburn
Author-email: contact@bhax.net
License: Apache 2.0
Platform: UNKNOWN
Classifier: Programming Language :: Python
Classifier: Programming Language :: Python :: 3
License-File: LICENSE
Requires-Dist: blessed
